<?xml version="1.0" encoding="utf-8"?>
<city actionsTitle="GUI/Edicts">
	<modifiers>
		<modifier>
			<effects>
				<loyaltyPerCity base="-6"/>
			</effects>
		</modifier>
	</modifiers>
	<actions>
		<tactic cooldown="10"
				durationInSeconds="0.1"
				interfaceSound="Interface/Edict"
				name="NovusImperium/ResourceEdict"
				requiredUpgrade="NovusImperium/ResourceEdict">
			<modifiers>
				<modifier visible="0">
					<effects>
						<influenceCost base="85"/>
					</effects>
				</modifier>
			</modifiers>
			<actorModifiers>
				<modifier>
					<effects>
						<addTrait duration="10" name="NovusImperium/ResourceEdict"/>
					</effects>
				</modifier>
			</actorModifiers>
			<strategyModifiers>
				<modifier>
					<effects>
						<increaseOreScore base="1.0"/>
						<increaseFoodScore base="1.0"/>
						<increaseEnergyScore base="1.0"/>
					</effects>
				</modifier>
			</strategyModifiers>	
		</tactic>
	</actions>
	<traits>
	</traits>
</city>
